{
    "schemes": [
        "http"
    ],
    "swagger": "2.0",
    "info": {
        "description": "REST API con Go + Gin · Auth JWT · PostgreSQL · Swagger",
        "title": "dev-test-api",
        "termsOfService": "http://swagger.io/terms/",
        "contact": {
            "name": "Felipe",
            "email": "felipe@example.com"
        },
        "license": {
            "name": "MIT",
            "url": "https://opensource.org/licenses/MIT"
        },
        "version": "1.0"
    },
    "host": "localhost:8080",
    "basePath": "/",
    "paths": {
        "/api/v1/auth/login": {
            "post": {
                "description": "Autentica un usuario y devuelve un token JWT",
                "consumes": [
                    "application/json"
                ],
                "produces": [
                    "application/json"
                ],
                "tags": [
                    "auth"
                ],
                "summary": "Iniciar sesión",
                "parameters": [
                    {
                        "description": "Credenciales de login",
                        "name": "body",
                        "in": "body",
                        "required": true,
                        "schema": {
                            "$ref": "#/definitions/auth.LoginRequest"
                        }
                    }
                ],
                "responses": {
                    "200": {
                        "description": "OK",
                        "schema": {
                            "$ref": "#/definitions/auth.AuthResponse"
                        }
                    },
                    "400": {
                        "description": "Bad Request",
                        "schema": {
                            "$ref": "#/definitions/apierr.APIError"
                        }
                    },
                    "401": {
                        "description": "Unauthorized",
                        "schema": {
                            "$ref": "#/definitions/apierr.APIError"
                        }
                    }
                }
            }
        },
        "/api/v1/auth/setup": {
            "post": {
                "description": "Crea el primer usuario admin del sistema. Solo funciona si no hay usuarios creados.",
                "consumes": [
                    "application/json"
                ],
                "produces": [
                    "application/json"
                ],
                "tags": [
                    "auth"
                ],
                "summary": "Inicializar sistema (primer usuario admin)",
                "parameters": [
                    {
                        "description": "Credenciales del admin inicial",
                        "name": "body",
                        "in": "body",
                        "required": true,
                        "schema": {
                            "$ref": "#/definitions/auth.SetupRequest"
                        }
                    }
                ],
                "responses": {
                    "201": {
                        "description": "Created",
                        "schema": {
                            "$ref": "#/definitions/auth.AuthResponse"
                        }
                    },
                    "400": {
                        "description": "Bad Request",
                        "schema": {
                            "$ref": "#/definitions/apierr.APIError"
                        }
                    },
                    "409": {
                        "description": "System Already Initialized",
                        "schema": {
                            "$ref": "#/definitions/apierr.APIError"
                        }
                    }
                }
            }
        },
        "/api/v1/auth/status": {
            "get": {
                "description": "Indica si el sistema ya fue inicializado (tiene al menos un usuario)",
                "produces": [
                    "application/json"
                ],
                "tags": [
                    "auth"
                ],
                "summary": "Estado del sistema",
                "responses": {
                    "200": {
                        "description": "OK",
                        "schema": {
                            "$ref": "#/definitions/auth.StatusResponse"
                        }
                    }
                }
            }
        },
        "/api/v1/profile": {
            "get": {
                "security": [
                    {
                        "BearerAuth": []
                    }
                ],
                "description": "Obtiene los datos del usuario autenticado",
                "produces": [
                    "application/json"
                ],
                "tags": [
                    "profile"
                ],
                "summary": "Obtener perfil",
                "responses": {
                    "200": {
                        "description": "OK",
                        "schema": {
                            "$ref": "#/definitions/users.UserResponse"
                        }
                    },
                    "401": {
                        "description": "Unauthorized",
                        "schema": {
                            "$ref": "#/definitions/apierr.APIError"
                        }
                    }
                }
            }
        },
        "/api/v1/progress/saved": {
            "get": {
                "security": [
                    {
                        "BearerAuth": []
                    }
                ],
                "description": "Lista todas las preguntas que el usuario ha guardado para repasar",
                "produces": [
                    "application/json"
                ],
                "tags": [
                    "progress"
                ],
                "summary": "Preguntas guardadas (con paginación)",
                "parameters": [
                    {
                        "type": "integer",
                        "description": "Número de página (default: 1)",
                        "name": "page",
                        "in": "query"
                    },
                    {
                        "type": "integer",
                        "description": "Elementos por página (default: 20, max: 100)",
                        "name": "perPage",
                        "in": "query"
                    },
                    {
                        "type": "string",
                        "description": "Campo de ordenación: updated_at, repetitions, ease_factor",
                        "name": "sortBy",
                        "in": "query"
                    },
                    {
                        "type": "string",
                        "description": "Dirección: asc o desc (default: desc)",
                        "name": "sortOrder",
                        "in": "query"
                    }
                ],
                "responses": {
                    "200": {
                        "description": "Preguntas guardadas (con paginación)",
                        "schema": {
                            "$ref": "#/definitions/response.Meta"
                        }
                    },
                    "401": {
                        "description": "Unauthorized",
                        "schema": {
                            "$ref": "#/definitions/apierr.APIError"
                        }
                    },
                    "422": {
                        "description": "Unprocessable Entity",
                        "schema": {
                            "$ref": "#/definitions/apierr.APIError"
                        }
                    }
                }
            }
        },
        "/api/v1/progress/upcoming": {
            "get": {
                "security": [
                    {
                        "BearerAuth": []
                    }
                ],
                "description": "Lista las preguntas marcadas para repasar cuyo próximo repaso es hoy",
                "produces": [
                    "application/json"
                ],
                "tags": [
                    "progress"
                ],
                "summary": "Preguntas pendientes (con paginación)",
                "parameters": [
                    {
                        "type": "integer",
                        "description": "Número de página (default: 1)",
                        "name": "page",
                        "in": "query"
                    },
                    {
                        "type": "integer",
                        "description": "Elementos por página (default: 20, max: 100)",
                        "name": "perPage",
                        "in": "query"
                    },
                    {
                        "type": "string",
                        "description": "Campo de ordenación: next_review_at, repetitions, ease_factor",
                        "name": "sortBy",
                        "in": "query"
                    },
                    {
                        "type": "string",
                        "description": "Dirección: asc o desc (default: asc)",
                        "name": "sortOrder",
                        "in": "query"
                    }
                ],
                "responses": {
                    "200": {
                        "description": "Preguntas pendientes (con paginación)",
                        "schema": {
                            "$ref": "#/definitions/response.Meta"
                        }
                    },
                    "401": {
                        "description": "Unauthorized",
                        "schema": {
                            "$ref": "#/definitions/apierr.APIError"
                        }
                    },
                    "422": {
                        "description": "Unprocessable Entity",
                        "schema": {
                            "$ref": "#/definitions/apierr.APIError"
                        }
                    }
                }
            }
        },
        "/api/v1/progress/{question_id}/answer": {
            "post": {
                "security": [
                    {
                        "BearerAuth": []
                    }
                ],
                "description": "Registra una respuesta correcta/incorrecta y actualiza el progreso SM-2",
                "consumes": [
                    "application/json"
                ],
                "produces": [
                    "application/json"
                ],
                "tags": [
                    "progress"
                ],
                "summary": "Responder pregunta",
                "parameters": [
                    {
                        "type": "string",
                        "description": "Question ID",
                        "name": "question_id",
                        "in": "path",
                        "required": true
                    },
                    {
                        "description": "Respuesta",
                        "name": "body",
                        "in": "body",
                        "required": true,
                        "schema": {
                            "$ref": "#/definitions/progress.AnswerRequest"
                        }
                    }
                ],
                "responses": {
                    "200": {
                        "description": "OK",
                        "schema": {
                            "$ref": "#/definitions/progress.ProgressResponse"
                        }
                    },
                    "400": {
                        "description": "Bad Request",
                        "schema": {
                            "$ref": "#/definitions/apierr.APIError"
                        }
                    },
                    "401": {
                        "description": "Unauthorized",
                        "schema": {
                            "$ref": "#/definitions/apierr.APIError"
                        }
                    }
                }
            }
        },
        "/api/v1/progress/{question_id}/toggle-save": {
            "post": {
                "security": [
                    {
                        "BearerAuth": []
                    }
                ],
                "description": "Alterna el estado is_saved de una pregunta para el usuario",
                "produces": [
                    "application/json"
                ],
                "tags": [
                    "progress"
                ],
                "summary": "Marcar/desmarcar pregunta",
                "parameters": [
                    {
                        "type": "string",
                        "description": "Question ID",
                        "name": "question_id",
                        "in": "path",
                        "required": true
                    }
                ],
                "responses": {
                    "200": {
                        "description": "OK",
                        "schema": {
                            "$ref": "#/definitions/progress.ProgressResponse"
                        }
                    },
                    "401": {
                        "description": "Unauthorized",
                        "schema": {
                            "$ref": "#/definitions/apierr.APIError"
                        }
                    },
                    "404": {
                        "description": "Not Found",
                        "schema": {
                            "$ref": "#/definitions/apierr.APIError"
                        }
                    }
                }
            }
        },
        "/api/v1/questions": {
            "get": {
                "security": [
                    {
                        "BearerAuth": []
                    }
                ],
                "description": "Lista todas las preguntas disponibles, con filtros opcionales",
                "produces": [
                    "application/json"
                ],
                "tags": [
                    "questions"
                ],
                "summary": "Listar preguntas (con paginación)",
                "parameters": [
                    {
                        "type": "integer",
                        "description": "Número de página (default: 1)",
                        "name": "page",
                        "in": "query"
                    },
                    {
                        "type": "integer",
                        "description": "Elementos por página (default: 20, max: 100)",
                        "name": "perPage",
                        "in": "query"
                    },
                    {
                        "type": "string",
                        "description": "Filtrar por tipo (single_choice, multiple_choice, code_completion)",
                        "name": "type",
                        "in": "query"
                    },
                    {
                        "type": "string",
                        "description": "Filtrar por dificultad (beginner, intermediate, advanced)",
                        "name": "difficulty",
                        "in": "query"
                    },
                    {
                        "type": "string",
                        "description": "Campo de ordenación: type, difficulty, created_at, updated_at",
                        "name": "sortBy",
                        "in": "query"
                    },
                    {
                        "type": "string",
                        "description": "Dirección: asc o desc (default: desc)",
                        "name": "sortOrder",
                        "in": "query"
                    }
                ],
                "responses": {
                    "200": {
                        "description": "Lista de preguntas (con paginación)",
                        "schema": {
                            "$ref": "#/definitions/response.Meta"
                        }
                    },
                    "401": {
                        "description": "Unauthorized",
                        "schema": {
                            "$ref": "#/definitions/apierr.APIError"
                        }
                    },
                    "422": {
                        "description": "Unprocessable Entity",
                        "schema": {
                            "$ref": "#/definitions/apierr.APIError"
                        }
                    }
                }
            },
            "post": {
                "security": [
                    {
                        "BearerAuth": []
                    }
                ],
                "description": "Crea una nueva pregunta con opciones o código",
                "consumes": [
                    "application/json"
                ],
                "produces": [
                    "application/json"
                ],
                "tags": [
                    "questions"
                ],
                "summary": "Crear pregunta (Admin)",
                "parameters": [
                    {
                        "description": "Datos de la pregunta",
                        "name": "body",
                        "in": "body",
                        "required": true,
                        "schema": {
                            "$ref": "#/definitions/questions.CreateQuestionRequest"
                        }
                    }
                ],
                "responses": {
                    "201": {
                        "description": "Created",
                        "schema": {
                            "$ref": "#/definitions/questions.QuestionResponse"
                        }
                    },
                    "400": {
                        "description": "Bad Request",
                        "schema": {
                            "$ref": "#/definitions/apierr.APIError"
                        }
                    },
                    "401": {
                        "description": "Unauthorized",
                        "schema": {
                            "$ref": "#/definitions/apierr.APIError"
                        }
                    },
                    "403": {
                        "description": "Forbidden",
                        "schema": {
                            "$ref": "#/definitions/apierr.APIError"
                        }
                    }
                }
            }
        },
        "/api/v1/questions/{id}": {
            "get": {
                "security": [
                    {
                        "BearerAuth": []
                    }
                ],
                "description": "Obtiene una pregunta por ID con todos sus detalles (opciones, código, temas)",
                "produces": [
                    "application/json"
                ],
                "tags": [
                    "questions"
                ],
                "summary": "Obtener pregunta",
                "parameters": [
                    {
                        "type": "string",
                        "description": "Question ID",
                        "name": "id",
                        "in": "path",
                        "required": true
                    }
                ],
                "responses": {
                    "200": {
                        "description": "OK",
                        "schema": {
                            "$ref": "#/definitions/questions.QuestionResponse"
                        }
                    },
                    "401": {
                        "description": "Unauthorized",
                        "schema": {
                            "$ref": "#/definitions/apierr.APIError"
                        }
                    },
                    "404": {
                        "description": "Not Found",
                        "schema": {
                            "$ref": "#/definitions/apierr.APIError"
                        }
                    }
                }
            },
            "put": {
                "security": [
                    {
                        "BearerAuth": []
                    }
                ],
                "description": "Actualiza una pregunta existente",
                "consumes": [
                    "application/json"
                ],
                "produces": [
                    "application/json"
                ],
                "tags": [
                    "questions"
                ],
                "summary": "Actualizar pregunta (Admin)",
                "parameters": [
                    {
                        "type": "string",
                        "description": "Question ID",
                        "name": "id",
                        "in": "path",
                        "required": true
                    },
                    {
                        "description": "Datos a actualizar",
                        "name": "body",
                        "in": "body",
                        "required": true,
                        "schema": {
                            "$ref": "#/definitions/questions.UpdateQuestionRequest"
                        }
                    }
                ],
                "responses": {
                    "200": {
                        "description": "OK",
                        "schema": {
                            "$ref": "#/definitions/questions.QuestionResponse"
                        }
                    },
                    "400": {
                        "description": "Bad Request",
                        "schema": {
                            "$ref": "#/definitions/apierr.APIError"
                        }
                    },
                    "401": {
                        "description": "Unauthorized",
                        "schema": {
                            "$ref": "#/definitions/apierr.APIError"
                        }
                    },
                    "403": {
                        "description": "Forbidden",
                        "schema": {
                            "$ref": "#/definitions/apierr.APIError"
                        }
                    },
                    "404": {
                        "description": "Not Found",
                        "schema": {
                            "$ref": "#/definitions/apierr.APIError"
                        }
                    }
                }
            },
            "delete": {
                "security": [
                    {
                        "BearerAuth": []
                    }
                ],
                "description": "Elimina una pregunta (soft delete)",
                "produces": [
                    "application/json"
                ],
                "tags": [
                    "questions"
                ],
                "summary": "Eliminar pregunta (Admin)",
                "parameters": [
                    {
                        "type": "string",
                        "description": "Question ID",
                        "name": "id",
                        "in": "path",
                        "required": true
                    }
                ],
                "responses": {
                    "200": {
                        "description": "OK",
                        "schema": {
                            "type": "object",
                            "additionalProperties": {
                                "type": "string"
                            }
                        }
                    },
                    "401": {
                        "description": "Unauthorized",
                        "schema": {
                            "$ref": "#/definitions/apierr.APIError"
                        }
                    },
                    "403": {
                        "description": "Forbidden",
                        "schema": {
                            "$ref": "#/definitions/apierr.APIError"
                        }
                    },
                    "404": {
                        "description": "Not Found",
                        "schema": {
                            "$ref": "#/definitions/apierr.APIError"
                        }
                    }
                }
            }
        },
        "/api/v1/sessions": {
            "get": {
                "security": [
                    {
                        "BearerAuth": []
                    }
                ],
                "description": "Lista las sesiones de estudio del usuario autenticado",
                "produces": [
                    "application/json"
                ],
                "tags": [
                    "sessions"
                ],
                "summary": "Listar sesiones (con paginación)",
                "parameters": [
                    {
                        "type": "integer",
                        "description": "Número de página (default: 1)",
                        "name": "page",
                        "in": "query"
                    },
                    {
                        "type": "integer",
                        "description": "Elementos por página (default: 20, max: 100)",
                        "name": "perPage",
                        "in": "query"
                    },
                    {
                        "type": "string",
                        "description": "Campo de ordenación: status, score, started_at, created_at",
                        "name": "sortBy",
                        "in": "query"
                    },
                    {
                        "type": "string",
                        "description": "Dirección: asc o desc (default: desc)",
                        "name": "sortOrder",
                        "in": "query"
                    }
                ],
                "responses": {
                    "200": {
                        "description": "Lista de sesiones (con paginación)",
                        "schema": {
                            "$ref": "#/definitions/response.Meta"
                        }
                    },
                    "401": {
                        "description": "Unauthorized",
                        "schema": {
                            "$ref": "#/definitions/apierr.APIError"
                        }
                    },
                    "422": {
                        "description": "Unprocessable Entity",
                        "schema": {
                            "$ref": "#/definitions/apierr.APIError"
                        }
                    }
                }
            },
            "post": {
                "security": [
                    {
                        "BearerAuth": []
                    }
                ],
                "description": "Crea una nueva sesión de estudio",
                "consumes": [
                    "application/json"
                ],
                "produces": [
                    "application/json"
                ],
                "tags": [
                    "sessions"
                ],
                "summary": "Crear sesión",
                "parameters": [
                    {
                        "description": "Datos de la sesión",
                        "name": "body",
                        "in": "body",
                        "required": true,
                        "schema": {
                            "$ref": "#/definitions/sessions.CreateSessionRequest"
                        }
                    }
                ],
                "responses": {
                    "201": {
                        "description": "Created",
                        "schema": {
                            "$ref": "#/definitions/sessions.SessionResponse"
                        }
                    },
                    "400": {
                        "description": "Bad Request",
                        "schema": {
                            "$ref": "#/definitions/apierr.APIError"
                        }
                    },
                    "401": {
                        "description": "Unauthorized",
                        "schema": {
                            "$ref": "#/definitions/apierr.APIError"
                        }
                    }
                }
            }
        },
        "/api/v1/sessions/{id}": {
            "get": {
                "security": [
                    {
                        "BearerAuth": []
                    }
                ],
                "description": "Obtiene el detalle de una sesión con sus respuestas",
                "produces": [
                    "application/json"
                ],
                "tags": [
                    "sessions"
                ],
                "summary": "Obtener sesión",
                "parameters": [
                    {
                        "type": "string",
                        "description": "Session ID",
                        "name": "id",
                        "in": "path",
                        "required": true
                    }
                ],
                "responses": {
                    "200": {
                        "description": "OK",
                        "schema": {
                            "$ref": "#/definitions/sessions.SessionDetailResponse"
                        }
                    },
                    "401": {
                        "description": "Unauthorized",
                        "schema": {
                            "$ref": "#/definitions/apierr.APIError"
                        }
                    },
                    "404": {
                        "description": "Not Found",
                        "schema": {
                            "$ref": "#/definitions/apierr.APIError"
                        }
                    }
                }
            }
        },
        "/api/v1/sessions/{id}/answer": {
            "post": {
                "security": [
                    {
                        "BearerAuth": []
                    }
                ],
                "description": "Registra la respuesta del usuario y actualiza el progreso SM-2",
                "consumes": [
                    "application/json"
                ],
                "produces": [
                    "application/json"
                ],
                "tags": [
                    "sessions"
                ],
                "summary": "Responder pregunta",
                "parameters": [
                    {
                        "type": "string",
                        "description": "Session ID",
                        "name": "id",
                        "in": "path",
                        "required": true
                    },
                    {
                        "description": "Respuesta",
                        "name": "body",
                        "in": "body",
                        "required": true,
                        "schema": {
                            "$ref": "#/definitions/sessions.AnswerRequest"
                        }
                    }
                ],
                "responses": {
                    "200": {
                        "description": "OK",
                        "schema": {
                            "$ref": "#/definitions/sessions.SessionAnswerResponse"
                        }
                    },
                    "400": {
                        "description": "Bad Request",
                        "schema": {
                            "$ref": "#/definitions/apierr.APIError"
                        }
                    },
                    "401": {
                        "description": "Unauthorized",
                        "schema": {
                            "$ref": "#/definitions/apierr.APIError"
                        }
                    },
                    "404": {
                        "description": "Not Found",
                        "schema": {
                            "$ref": "#/definitions/apierr.APIError"
                        }
                    }
                }
            }
        },
        "/api/v1/sessions/{id}/finish": {
            "put": {
                "security": [
                    {
                        "BearerAuth": []
                    }
                ],
                "description": "Finaliza una sesión — el score se calcula automáticamente",
                "produces": [
                    "application/json"
                ],
                "tags": [
                    "sessions"
                ],
                "summary": "Finalizar sesión",
                "parameters": [
                    {
                        "type": "string",
                        "description": "Session ID",
                        "name": "id",
                        "in": "path",
                        "required": true
                    }
                ],
                "responses": {
                    "200": {
                        "description": "OK",
                        "schema": {
                            "$ref": "#/definitions/sessions.SessionResponse"
                        }
                    },
                    "401": {
                        "description": "Unauthorized",
                        "schema": {
                            "$ref": "#/definitions/apierr.APIError"
                        }
                    },
                    "404": {
                        "description": "Not Found",
                        "schema": {
                            "$ref": "#/definitions/apierr.APIError"
                        }
                    },
                    "409": {
                        "description": "Conflict",
                        "schema": {
                            "$ref": "#/definitions/apierr.APIError"
                        }
                    }
                }
            }
        },
        "/api/v1/sessions/{id}/next": {
            "get": {
                "security": [
                    {
                        "BearerAuth": []
                    }
                ],
                "description": "Obtiene la siguiente pregunta sin responder en la sesión",
                "produces": [
                    "application/json"
                ],
                "tags": [
                    "sessions"
                ],
                "summary": "Siguiente pregunta",
                "parameters": [
                    {
                        "type": "string",
                        "description": "Session ID",
                        "name": "id",
                        "in": "path",
                        "required": true
                    }
                ],
                "responses": {
                    "200": {
                        "description": "OK",
                        "schema": {
                            "$ref": "#/definitions/sessions.NextQuestionResponse"
                        }
                    },
                    "401": {
                        "description": "Unauthorized",
                        "schema": {
                            "$ref": "#/definitions/apierr.APIError"
                        }
                    },
                    "404": {
                        "description": "Not Found",
                        "schema": {
                            "$ref": "#/definitions/apierr.APIError"
                        }
                    }
                }
            }
        },
        "/api/v1/topics": {
            "get": {
                "security": [
                    {
                        "BearerAuth": []
                    }
                ],
                "description": "Lista los temas según el rol del usuario. Admin ve solo temas del sistema (is_system=true). Usuarios normales ven solo sus propios temas personalizados (is_system=false).",
                "produces": [
                    "application/json"
                ],
                "tags": [
                    "topics"
                ],
                "summary": "Listar temas (con paginación)",
                "parameters": [
                    {
                        "type": "integer",
                        "description": "Número de página (default: 1)",
                        "name": "page",
                        "in": "query"
                    },
                    {
                        "type": "integer",
                        "description": "Elementos por página (default: 20, max: 100)",
                        "name": "perPage",
                        "in": "query"
                    },
                    {
                        "type": "string",
                        "description": "Campo de ordenación: name, slug, category, created_at",
                        "name": "sortBy",
                        "in": "query"
                    },
                    {
                        "type": "string",
                        "description": "Dirección: asc o desc (default: desc)",
                        "name": "sortOrder",
                        "in": "query"
                    }
                ],
                "responses": {
                    "200": {
                        "description": "Lista de temas (con paginación)",
                        "schema": {
                            "$ref": "#/definitions/response.Meta"
                        }
                    },
                    "401": {
                        "description": "Unauthorized",
                        "schema": {
                            "$ref": "#/definitions/apierr.APIError"
                        }
                    },
                    "422": {
                        "description": "Unprocessable Entity",
                        "schema": {
                            "$ref": "#/definitions/apierr.APIError"
                        }
                    }
                }
            },
            "post": {
                "security": [
                    {
                        "BearerAuth": []
                    }
                ],
                "description": "Crea un nuevo tema. Admin crea temas del sistema (is_system=true), usuarios normales crean temas personalizados (is_system=false).",
                "consumes": [
                    "application/json"
                ],
                "produces": [
                    "application/json"
                ],
                "tags": [
                    "topics"
                ],
                "summary": "Crear tema",
                "parameters": [
                    {
                        "description": "Datos del tema",
                        "name": "body",
                        "in": "body",
                        "required": true,
                        "schema": {
                            "$ref": "#/definitions/topics.CreateTopicRequest"
                        }
                    }
                ],
                "responses": {
                    "201": {
                        "description": "Created",
                        "schema": {
                            "$ref": "#/definitions/topics.TopicResponse"
                        }
                    },
                    "400": {
                        "description": "Bad Request",
                        "schema": {
                            "$ref": "#/definitions/apierr.APIError"
                        }
                    },
                    "401": {
                        "description": "Unauthorized",
                        "schema": {
                            "$ref": "#/definitions/apierr.APIError"
                        }
                    },
                    "409": {
                        "description": "Conflict",
                        "schema": {
                            "$ref": "#/definitions/apierr.APIError"
                        }
                    }
                }
            }
        },
        "/api/v1/topics/{id}": {
            "get": {
                "security": [
                    {
                        "BearerAuth": []
                    }
                ],
                "description": "Obtiene un tema por ID. Admin solo puede ver temas del sistema (is_system=true). Usuarios normales pueden ver temas del sistema y sus propios temas.",
                "produces": [
                    "application/json"
                ],
                "tags": [
                    "topics"
                ],
                "summary": "Obtener tema",
                "parameters": [
                    {
                        "type": "string",
                        "description": "Topic ID",
                        "name": "id",
                        "in": "path",
                        "required": true
                    }
                ],
                "responses": {
                    "200": {
                        "description": "OK",
                        "schema": {
                            "$ref": "#/definitions/topics.TopicResponse"
                        }
                    },
                    "401": {
                        "description": "Unauthorized",
                        "schema": {
                            "$ref": "#/definitions/apierr.APIError"
                        }
                    },
                    "404": {
                        "description": "Not Found",
                        "schema": {
                            "$ref": "#/definitions/apierr.APIError"
                        }
                    }
                }
            },
            "put": {
                "security": [
                    {
                        "BearerAuth": []
                    }
                ],
                "description": "Actualiza un tema existente. Admin solo puede modificar temas del sistema (is_system=true). Usuarios normales solo pueden modificar sus propios temas (is_system=false).",
                "consumes": [
                    "application/json"
                ],
                "produces": [
                    "application/json"
                ],
                "tags": [
                    "topics"
                ],
                "summary": "Actualizar tema",
                "parameters": [
                    {
                        "type": "string",
                        "description": "Topic ID",
                        "name": "id",
                        "in": "path",
                        "required": true
                    },
                    {
                        "description": "Datos a actualizar",
                        "name": "body",
                        "in": "body",
                        "required": true,
                        "schema": {
                            "$ref": "#/definitions/topics.UpdateTopicRequest"
                        }
                    }
                ],
                "responses": {
                    "200": {
                        "description": "OK",
                        "schema": {
                            "$ref": "#/definitions/topics.TopicResponse"
                        }
                    },
                    "400": {
                        "description": "Bad Request",
                        "schema": {
                            "$ref": "#/definitions/apierr.APIError"
                        }
                    },
                    "401": {
                        "description": "Unauthorized",
                        "schema": {
                            "$ref": "#/definitions/apierr.APIError"
                        }
                    },
                    "403": {
                        "description": "Forbidden",
                        "schema": {
                            "$ref": "#/definitions/apierr.APIError"
                        }
                    },
                    "404": {
                        "description": "Not Found",
                        "schema": {
                            "$ref": "#/definitions/apierr.APIError"
                        }
                    }
                }
            },
            "delete": {
                "security": [
                    {
                        "BearerAuth": []
                    }
                ],
                "description": "Elimina un tema. Admin solo puede eliminar temas del sistema (is_system=true). Usuarios normales solo pueden eliminar sus propios temas (is_system=false).",
                "produces": [
                    "application/json"
                ],
                "tags": [
                    "topics"
                ],
                "summary": "Eliminar tema",
                "parameters": [
                    {
                        "type": "string",
                        "description": "Topic ID",
                        "name": "id",
                        "in": "path",
                        "required": true
                    }
                ],
                "responses": {
                    "200": {
                        "description": "OK",
                        "schema": {
                            "type": "object",
                            "additionalProperties": {
                                "type": "string"
                            }
                        }
                    },
                    "401": {
                        "description": "Unauthorized",
                        "schema": {
                            "$ref": "#/definitions/apierr.APIError"
                        }
                    },
                    "403": {
                        "description": "Forbidden",
                        "schema": {
                            "$ref": "#/definitions/apierr.APIError"
                        }
                    },
                    "404": {
                        "description": "Not Found",
                        "schema": {
                            "$ref": "#/definitions/apierr.APIError"
                        }
                    }
                }
            }
        },
        "/api/v1/users": {
            "get": {
                "security": [
                    {
                        "BearerAuth": []
                    }
                ],
                "description": "Lista todos los usuarios",
                "produces": [
                    "application/json"
                ],
                "tags": [
                    "users"
                ],
                "summary": "Listar usuarios (con paginación) (Admin)",
                "parameters": [
                    {
                        "type": "integer",
                        "description": "Número de página (default: 1)",
                        "name": "page",
                        "in": "query"
                    },
                    {
                        "type": "integer",
                        "description": "Elementos por página (default: 20, max: 100)",
                        "name": "perPage",
                        "in": "query"
                    },
                    {
                        "type": "string",
                        "description": "Campo de ordenación: email, created_at, updated_at",
                        "name": "sortBy",
                        "in": "query"
                    },
                    {
                        "type": "string",
                        "description": "Dirección: asc o desc (default: desc)",
                        "name": "sortOrder",
                        "in": "query"
                    }
                ],
                "responses": {
                    "200": {
                        "description": "Lista de usuarios (con paginación)",
                        "schema": {
                            "$ref": "#/definitions/response.Meta"
                        }
                    },
                    "401": {
                        "description": "Unauthorized",
                        "schema": {
                            "$ref": "#/definitions/apierr.APIError"
                        }
                    },
                    "403": {
                        "description": "Forbidden",
                        "schema": {
                            "$ref": "#/definitions/apierr.APIError"
                        }
                    },
                    "422": {
                        "description": "Unprocessable Entity",
                        "schema": {
                            "$ref": "#/definitions/apierr.APIError"
                        }
                    }
                }
            },
            "post": {
                "security": [
                    {
                        "BearerAuth": []
                    }
                ],
                "description": "Crea un nuevo usuario",
                "consumes": [
                    "application/json"
                ],
                "produces": [
                    "application/json"
                ],
                "tags": [
                    "users"
                ],
                "summary": "Crear usuario (Admin)",
                "parameters": [
                    {
                        "description": "Datos del usuario",
                        "name": "body",
                        "in": "body",
                        "required": true,
                        "schema": {
                            "$ref": "#/definitions/users.CreateUserRequest"
                        }
                    }
                ],
                "responses": {
                    "201": {
                        "description": "Created",
                        "schema": {
                            "$ref": "#/definitions/users.UserResponse"
                        }
                    },
                    "400": {
                        "description": "Bad Request",
                        "schema": {
                            "$ref": "#/definitions/apierr.APIError"
                        }
                    },
                    "401": {
                        "description": "Unauthorized",
                        "schema": {
                            "$ref": "#/definitions/apierr.APIError"
                        }
                    },
                    "403": {
                        "description": "Forbidden",
                        "schema": {
                            "$ref": "#/definitions/apierr.APIError"
                        }
                    },
                    "409": {
                        "description": "Conflict",
                        "schema": {
                            "$ref": "#/definitions/apierr.APIError"
                        }
                    }
                }
            }
        },
        "/api/v1/users/{id}": {
            "get": {
                "security": [
                    {
                        "BearerAuth": []
                    }
                ],
                "description": "Obtiene un usuario por ID",
                "produces": [
                    "application/json"
                ],
                "tags": [
                    "users"
                ],
                "summary": "Obtener usuario (Admin)",
                "parameters": [
                    {
                        "type": "string",
                        "description": "User ID",
                        "name": "id",
                        "in": "path",
                        "required": true
                    }
                ],
                "responses": {
                    "200": {
                        "description": "OK",
                        "schema": {
                            "$ref": "#/definitions/users.UserResponse"
                        }
                    },
                    "401": {
                        "description": "Unauthorized",
                        "schema": {
                            "$ref": "#/definitions/apierr.APIError"
                        }
                    },
                    "403": {
                        "description": "Forbidden",
                        "schema": {
                            "$ref": "#/definitions/apierr.APIError"
                        }
                    },
                    "404": {
                        "description": "Not Found",
                        "schema": {
                            "$ref": "#/definitions/apierr.APIError"
                        }
                    }
                }
            },
            "put": {
                "security": [
                    {
                        "BearerAuth": []
                    }
                ],
                "description": "Actualiza los datos de un usuario",
                "consumes": [
                    "application/json"
                ],
                "produces": [
                    "application/json"
                ],
                "tags": [
                    "users"
                ],
                "summary": "Actualizar usuario (Admin)",
                "parameters": [
                    {
                        "type": "string",
                        "description": "User ID",
                        "name": "id",
                        "in": "path",
                        "required": true
                    },
                    {
                        "description": "Datos a actualizar",
                        "name": "body",
                        "in": "body",
                        "required": true,
                        "schema": {
                            "$ref": "#/definitions/users.UpdateUserRequest"
                        }
                    }
                ],
                "responses": {
                    "200": {
                        "description": "OK",
                        "schema": {
                            "$ref": "#/definitions/users.UserResponse"
                        }
                    },
                    "400": {
                        "description": "Bad Request",
                        "schema": {
                            "$ref": "#/definitions/apierr.APIError"
                        }
                    },
                    "401": {
                        "description": "Unauthorized",
                        "schema": {
                            "$ref": "#/definitions/apierr.APIError"
                        }
                    },
                    "403": {
                        "description": "Forbidden",
                        "schema": {
                            "$ref": "#/definitions/apierr.APIError"
                        }
                    },
                    "404": {
                        "description": "Not Found",
                        "schema": {
                            "$ref": "#/definitions/apierr.APIError"
                        }
                    }
                }
            },
            "delete": {
                "security": [
                    {
                        "BearerAuth": []
                    }
                ],
                "description": "Soft-delete de un usuario",
                "produces": [
                    "application/json"
                ],
                "tags": [
                    "users"
                ],
                "summary": "Eliminar usuario (Admin)",
                "parameters": [
                    {
                        "type": "string",
                        "description": "User ID",
                        "name": "id",
                        "in": "path",
                        "required": true
                    }
                ],
                "responses": {
                    "200": {
                        "description": "OK",
                        "schema": {
                            "type": "object",
                            "additionalProperties": {
                                "type": "string"
                            }
                        }
                    },
                    "401": {
                        "description": "Unauthorized",
                        "schema": {
                            "$ref": "#/definitions/apierr.APIError"
                        }
                    },
                    "403": {
                        "description": "Forbidden",
                        "schema": {
                            "$ref": "#/definitions/apierr.APIError"
                        }
                    },
                    "404": {
                        "description": "Not Found",
                        "schema": {
                            "$ref": "#/definitions/apierr.APIError"
                        }
                    }
                }
            }
        },
        "/health": {
            "get": {
                "description": "Verifica que el servidor esté corriendo",
                "produces": [
                    "application/json"
                ],
                "tags": [
                    "health"
                ],
                "summary": "Health check",
                "responses": {
                    "200": {
                        "description": "OK",
                        "schema": {
                            "type": "object",
                            "additionalProperties": {
                                "type": "string"
                            }
                        }
                    }
                }
            }
        }
    },
    "definitions": {
        "apierr.APIError": {
            "type": "object",
            "properties": {
                "detail": {
                    "type": "string"
                },
                "instance": {
                    "type": "string"
                },
                "status": {
                    "type": "integer"
                },
                "title": {
                    "type": "string"
                },
                "type": {
                    "type": "string"
                }
            }
        },
        "auth.AuthResponse": {
            "type": "object",
            "properties": {
                "token": {
                    "type": "string"
                },
                "user": {
                    "$ref": "#/definitions/users.UserResponse"
                }
            }
        },
        "auth.LoginRequest": {
            "type": "object",
            "required": [
                "email",
                "password"
            ],
            "properties": {
                "email": {
                    "type": "string"
                },
                "password": {
                    "type": "string",
                    "minLength": 1
                }
            }
        },
        "auth.SetupRequest": {
            "type": "object",
            "required": [
                "email",
                "password"
            ],
            "properties": {
                "email": {
                    "type": "string"
                },
                "password": {
                    "type": "string",
                    "maxLength": 72,
                    "minLength": 8
                }
            }
        },
        "auth.StatusResponse": {
            "type": "object",
            "properties": {
                "initialized": {
                    "type": "boolean"
                }
            }
        },
        "progress.AnswerRequest": {
            "type": "object",
            "required": [
                "isCorrect"
            ],
            "properties": {
                "isCorrect": {
                    "type": "boolean"
                }
            }
        },
        "progress.ProgressResponse": {
            "type": "object",
            "properties": {
                "easeFactor": {
                    "type": "number"
                },
                "intervalDays": {
                    "type": "integer"
                },
                "isMastered": {
                    "type": "boolean"
                },
                "isSaved": {
                    "type": "boolean"
                },
                "lastReviewedAt": {
                    "type": "string"
                },
                "nextReviewAt": {
                    "type": "string"
                },
                "questionId": {
                    "type": "string"
                },
                "repetitions": {
                    "type": "integer"
                }
            }
        },
        "questions.CodeChallengeResponse": {
            "type": "object",
            "properties": {
                "expectedOutput": {
                    "type": "string"
                },
                "id": {
                    "type": "string"
                },
                "language": {
                    "type": "string"
                },
                "starterCode": {
                    "type": "string"
                },
                "testCases": {
                    "type": "string"
                }
            }
        },
        "questions.CreateOptionReq": {
            "type": "object",
            "required": [
                "content"
            ],
            "properties": {
                "content": {
                    "type": "string"
                },
                "isCorrect": {
                    "type": "boolean"
                }
            }
        },
        "questions.CreateQuestionRequest": {
            "type": "object",
            "required": [
                "content",
                "difficulty",
                "topicIds",
                "type"
            ],
            "properties": {
                "content": {
                    "type": "string"
                },
                "difficulty": {
                    "type": "string",
                    "enum": [
                        "beginner",
                        "intermediate",
                        "advanced"
                    ]
                },
                "expectedOutput": {
                    "type": "string"
                },
                "explanation": {
                    "type": "string"
                },
                "language": {
                    "type": "string"
                },
                "options": {
                    "type": "array",
                    "items": {
                        "$ref": "#/definitions/questions.CreateOptionReq"
                    }
                },
                "source": {
                    "type": "string",
                    "enum": [
                        "ai_generated",
                        "manual",
                        "imported"
                    ]
                },
                "starterCode": {
                    "type": "string"
                },
                "testCases": {
                    "type": "string"
                },
                "topicIds": {
                    "type": "array",
                    "minItems": 1,
                    "items": {
                        "type": "string"
                    }
                },
                "type": {
                    "type": "string",
                    "enum": [
                        "single_choice",
                        "multiple_choice",
                        "code_completion"
                    ]
                }
            }
        },
        "questions.OptionResponse": {
            "type": "object",
            "properties": {
                "content": {
                    "type": "string"
                },
                "id": {
                    "type": "string"
                },
                "isCorrect": {
                    "type": "boolean"
                }
            }
        },
        "questions.QuestionResponse": {
            "type": "object",
            "properties": {
                "codeChallenge": {
                    "$ref": "#/definitions/questions.CodeChallengeResponse"
                },
                "content": {
                    "type": "string"
                },
                "createdAt": {
                    "type": "string"
                },
                "difficulty": {
                    "type": "string"
                },
                "explanation": {
                    "type": "string"
                },
                "id": {
                    "type": "string"
                },
                "isPublic": {
                    "type": "boolean"
                },
                "options": {
                    "type": "array",
                    "items": {
                        "$ref": "#/definitions/questions.OptionResponse"
                    }
                },
                "source": {
                    "type": "string"
                },
                "topics": {
                    "type": "array",
                    "items": {
                        "$ref": "#/definitions/questions.TopicInfo"
                    }
                },
                "type": {
                    "type": "string"
                },
                "updatedAt": {
                    "type": "string"
                },
                "userId": {
                    "type": "string"
                }
            }
        },
        "questions.TopicInfo": {
            "type": "object",
            "properties": {
                "id": {
                    "type": "string"
                },
                "name": {
                    "type": "string"
                },
                "slug": {
                    "type": "string"
                }
            }
        },
        "questions.UpdateQuestionRequest": {
            "type": "object",
            "properties": {
                "content": {
                    "type": "string"
                },
                "difficulty": {
                    "type": "string",
                    "enum": [
                        "beginner",
                        "intermediate",
                        "advanced"
                    ]
                },
                "expectedOutput": {
                    "type": "string"
                },
                "explanation": {
                    "type": "string"
                },
                "language": {
                    "type": "string"
                },
                "options": {
                    "type": "array",
                    "items": {
                        "$ref": "#/definitions/questions.CreateOptionReq"
                    }
                },
                "starterCode": {
                    "type": "string"
                },
                "testCases": {
                    "type": "string"
                },
                "topicIds": {
                    "type": "array",
                    "items": {
                        "type": "string"
                    }
                }
            }
        },
        "response.Meta": {
            "type": "object",
            "properties": {
                "page": {
                    "type": "integer"
                },
                "per_page": {
                    "type": "integer"
                },
                "total": {
                    "type": "integer"
                }
            }
        },
        "sessions.AnswerRequest": {
            "type": "object",
            "required": [
                "questionId"
            ],
            "properties": {
                "answerText": {
                    "type": "string"
                },
                "isCorrect": {
                    "type": "boolean"
                },
                "questionId": {
                    "type": "string"
                },
                "responseTimeMs": {
                    "type": "integer"
                },
                "selectedOptions": {
                    "type": "array",
                    "items": {
                        "type": "string"
                    }
                }
            }
        },
        "sessions.CreateSessionRequest": {
            "type": "object",
            "required": [
                "difficulty",
                "mode",
                "name",
                "topicIds"
            ],
            "properties": {
                "difficulty": {
                    "type": "string",
                    "enum": [
                        "beginner",
                        "intermediate",
                        "advanced"
                    ]
                },
                "mode": {
                    "type": "string",
                    "enum": [
                        "generate",
                        "review"
                    ]
                },
                "name": {
                    "type": "string",
                    "maxLength": 200,
                    "minLength": 1
                },
                "questionLimit": {
                    "type": "integer",
                    "maximum": 50,
                    "minimum": 1
                },
                "topicIds": {
                    "type": "array",
                    "minItems": 1,
                    "items": {
                        "type": "string"
                    }
                }
            }
        },
        "sessions.NextQuestionResponse": {
            "type": "object",
            "properties": {
                "question": {
                    "$ref": "#/definitions/questions.QuestionResponse"
                }
            }
        },
        "sessions.SessionAnswerResponse": {
            "type": "object",
            "properties": {
                "aiFeedback": {
                    "type": "string"
                },
                "answerText": {
                    "type": "string"
                },
                "createdAt": {
                    "type": "string"
                },
                "id": {
                    "type": "string"
                },
                "isCorrect": {
                    "type": "boolean"
                },
                "question": {
                    "$ref": "#/definitions/questions.QuestionResponse"
                },
                "questionId": {
                    "type": "string"
                },
                "responseTimeMs": {
                    "type": "integer"
                },
                "selectedOptions": {
                    "type": "array",
                    "items": {
                        "type": "string"
                    }
                }
            }
        },
        "sessions.SessionDetailResponse": {
            "type": "object",
            "properties": {
                "answers": {
                    "type": "array",
                    "items": {
                        "$ref": "#/definitions/sessions.SessionAnswerResponse"
                    }
                },
                "session": {
                    "$ref": "#/definitions/sessions.SessionResponse"
                }
            }
        },
        "sessions.SessionResponse": {
            "type": "object",
            "properties": {
                "answerCount": {
                    "type": "integer"
                },
                "createdAt": {
                    "type": "string"
                },
                "difficulty": {
                    "type": "string"
                },
                "finishedAt": {
                    "type": "string"
                },
                "id": {
                    "type": "string"
                },
                "mode": {
                    "type": "string"
                },
                "name": {
                    "type": "string"
                },
                "questionLimit": {
                    "type": "integer"
                },
                "score": {
                    "type": "number"
                },
                "startedAt": {
                    "type": "string"
                },
                "status": {
                    "type": "string"
                },
                "topics": {
                    "type": "array",
                    "items": {
                        "$ref": "#/definitions/sessions.TopicInfo"
                    }
                },
                "updatedAt": {
                    "type": "string"
                },
                "userId": {
                    "type": "string"
                }
            }
        },
        "sessions.TopicInfo": {
            "type": "object",
            "properties": {
                "id": {
                    "type": "string"
                },
                "name": {
                    "type": "string"
                },
                "slug": {
                    "type": "string"
                }
            }
        },
        "topics.CreateTopicRequest": {
            "type": "object",
            "required": [
                "category",
                "name",
                "slug"
            ],
            "properties": {
                "category": {
                    "type": "string",
                    "maxLength": 50,
                    "minLength": 1
                },
                "name": {
                    "type": "string",
                    "maxLength": 150,
                    "minLength": 1
                },
                "slug": {
                    "type": "string",
                    "maxLength": 100,
                    "minLength": 2
                }
            }
        },
        "topics.TopicResponse": {
            "type": "object",
            "properties": {
                "category": {
                    "type": "string"
                },
                "createdAt": {
                    "type": "string"
                },
                "createdBy": {
                    "type": "string"
                },
                "id": {
                    "type": "string"
                },
                "isSystem": {
                    "type": "boolean"
                },
                "name": {
                    "type": "string"
                },
                "slug": {
                    "type": "string"
                },
                "updatedAt": {
                    "type": "string"
                }
            }
        },
        "topics.UpdateTopicRequest": {
            "type": "object",
            "properties": {
                "category": {
                    "type": "string",
                    "maxLength": 50,
                    "minLength": 1
                },
                "name": {
                    "type": "string",
                    "maxLength": 150,
                    "minLength": 1
                }
            }
        },
        "users.CreateUserRequest": {
            "type": "object",
            "required": [
                "email",
                "password"
            ],
            "properties": {
                "email": {
                    "type": "string"
                },
                "isAdmin": {
                    "type": "boolean"
                },
                "password": {
                    "type": "string",
                    "maxLength": 72,
                    "minLength": 8
                }
            }
        },
        "users.UpdateUserRequest": {
            "type": "object",
            "properties": {
                "isAdmin": {
                    "type": "boolean"
                },
                "password": {
                    "type": "string",
                    "maxLength": 72,
                    "minLength": 8
                }
            }
        },
        "users.UserResponse": {
            "type": "object",
            "properties": {
                "createdAt": {
                    "type": "string"
                },
                "email": {
                    "type": "string"
                },
                "id": {
                    "type": "string"
                },
                "isAdmin": {
                    "type": "boolean"
                },
                "updatedAt": {
                    "type": "string"
                }
            }
        }
    },
    "securityDefinitions": {
        "BearerAuth": {
            "description": "JWT token. Prefix with \"Bearer \". Example: \"Bearer eyJhbG...\"",
            "type": "apiKey",
            "name": "Authorization",
            "in": "header"
        }
    }
}